pytabulate/__init__.py
pytabulate/pytabulate.py
pytabulate/utility.py
pytabulate-1.0.2a0.dist-info/LICENSE
pytabulate-1.0.2a0.dist-info/METADATA
pytabulate-1.0.2a0.dist-info/WHEEL
pytabulate-1.0.2a0.dist-info/top_level.txt
pytabulate-1.0.2a0.dist-info/RECORD
