Metadata-Version: 2.1
Name: pytabulate
Version: 1.0.2a0
Summary: understand your table datasets.
Home-page: UNKNOWN
Author: Umar Yousafzai
Author-email: umaryousafzai9@gmail.com
License: UNKNOWN
Platform: UNKNOWN
Classifier: Programming Language :: Python :: 3
Classifier: License :: OSI Approved :: MIT License
Classifier: Operating System :: OS Independent
Requires-Python: >=3.6
